RequestJsonValidator/__init__.py
RequestJsonValidator/decorators.py
DrfRequestJsonValidator-0.0.2.dist-info/LICENSE
DrfRequestJsonValidator-0.0.2.dist-info/METADATA
DrfRequestJsonValidator-0.0.2.dist-info/WHEEL
DrfRequestJsonValidator-0.0.2.dist-info/top_level.txt
DrfRequestJsonValidator-0.0.2.dist-info/RECORD
