Metadata-Version: 2.1
Name: DrfRequestJsonValidator
Version: 0.0.2
Summary: A package use for validate json payload with jsonschema
Home-page: https://github.com/lixujia/DrfRequestJsonValidator
Author: Li Xujia
Author-email: lixujia.cn@gmail.com
License: UNKNOWN
Platform: UNKNOWN
Classifier: Programming Language :: Python :: 3
Classifier: License :: OSI Approved :: MIT License
Classifier: Operating System :: OS Independent
